pygmtools/__init__.py
pygmtools/benchmark.py
pygmtools/c_astar.cpython-310-x86_64-linux-gnu.so
pygmtools/classic_solvers.py
pygmtools/dataset.py
pygmtools/dataset_config.py
pygmtools/jittor_backend.py
pygmtools/jittor_modules.py
pygmtools/linear_solvers.py
pygmtools/mindspore_backend.py
pygmtools/multi_graph_solvers.py
pygmtools/neural_solvers.py
pygmtools/numpy_backend.py
pygmtools/numpy_modules.py
pygmtools/paddle_backend.py
pygmtools/paddle_modules.py
pygmtools/pytorch_astar_modules.py
pygmtools/pytorch_backend.py
pygmtools/pytorch_modules.py
pygmtools/tensorflow_backend.py
pygmtools/tensorflow_modules.py
pygmtools/utils.py
pygmtools/c_astar_src/build_c_astar.py
pygmtools/c_astar_src/c_astar.cpp
pygmtools/c_astar_src/c_astar.cpython-310-x86_64-linux-gnu.so
pygmtools/c_astar_src/c_astar.pyx
pygmtools/c_astar_src/c_astar_setup.py
pygmtools/c_astar_src/priority_queue.hpp
pygmtools-0.5.5.dist-info/licenses/LICENSE
pygmtools-0.5.5.dist-info/METADATA
pygmtools-0.5.5.dist-info/WHEEL
pygmtools-0.5.5.dist-info/top_level.txt
pygmtools-0.5.5.dist-info/RECORD
