Metadata-Version: 2.1
Name: pygmtools
Version: 0.5.5
Summary: pygmtools provides graph matching solvers in Python API and supports numpy and pytorch backends. pygmtools also provides dataset API for standard graph matching benchmarks.
Home-page: https://pygmtools.readthedocs.io/
Author: ThinkLab at SJTU
License: Mulan PSL v2
Classifier: License :: OSI Approved :: Mulan Permissive Software License v2 (MulanPSL-2.0)
Classifier: Programming Language :: Python
Classifier: Programming Language :: Python :: 3
Classifier: Programming Language :: Python :: 3.8
Classifier: Programming Language :: Python :: 3.9
Classifier: Programming Language :: Python :: 3.10
Classifier: Programming Language :: Python :: 3 :: Only
Classifier: Programming Language :: Python :: Implementation :: CPython
Classifier: Operating System :: Microsoft :: Windows
Classifier: Operating System :: POSIX
Classifier: Operating System :: Unix
Classifier: Operating System :: MacOS
Classifier: Environment :: GPU :: NVIDIA CUDA
Classifier: Environment :: Console
Classifier: Topic :: Scientific/Engineering :: Artificial Intelligence
Classifier: Topic :: Scientific/Engineering :: Image Recognition
Classifier: Topic :: Scientific/Engineering :: Mathematics
Requires-Python: >=3.8
License-File: LICENSE
Requires-Dist: requests>=2.25.1
Requires-Dist: scipy>=1.4.1
Requires-Dist: Pillow>=7.2.0
Requires-Dist: numpy>=1.18.5
Requires-Dist: easydict>=1.7
Requires-Dist: appdirs>=1.4.4
Requires-Dist: tqdm>=4.64.1
Requires-Dist: async-timeout
Requires-Dist: aiohttp
Requires-Dist: networkx>=2.8.8
